sentinelmft/__init__.py
sentinelmft/cli.py
sentinelmft/config.py
sentinelmft/logging_utils.py
sentinelmft/ai/anomaly.py
sentinelmft/ai/features.py
sentinelmft/crypto/aesgcm.py
sentinelmft/firewall/policy.py
sentinelmft/transfer/gcs.py
sentinelmft/transfer/local.py
sentinelmft-0.1.4.dist-info/METADATA
sentinelmft-0.1.4.dist-info/WHEEL
sentinelmft-0.1.4.dist-info/top_level.txt
sentinelmft-0.1.4.dist-info/RECORD
