Metadata-Version: 2.4
Name: sentinelmft
Version: 0.1.4
Summary: AI-powered secure managed file transfer (GCS + AES-256-GCM + anomaly detection)
Author: Raghava Chellu
License: MIT
Project-URL: Homepage, https://github.com/RaghavaCh440/sentinelmft
Project-URL: Documentation, https://github.com/RaghavaCh440/sentinelmft#readme
Project-URL: Source, https://github.com/RaghavaCh440/sentinelmft
Project-URL: Issues, https://github.com/RaghavaCh440/sentinelmft/issues
Keywords: mft,gcp,gcs,encryption,aes-gcm,anomaly-detection,devsecops
Classifier: Programming Language :: Python :: 3
Classifier: License :: OSI Approved :: MIT License
Classifier: Operating System :: OS Independent
Classifier: Topic :: Security :: Cryptography
Classifier: Topic :: System :: Networking
Classifier: Intended Audience :: Developers
Requires-Python: >=3.9
